<?xml version="1.0" encoding="utf-8"?>
<PRONOM-Report xmlns="http://pronom.nationalarchives.gov.uk">
  <report_format_detail>
    <FileFormat>
      <FormatID>1949</FormatID>
      <FormatName>VectorWorks</FormatName>
      <FormatVersion>9</FormatVersion>
      <FormatAliases>
      </FormatAliases>
      <FormatFamilies>
      </FormatFamilies>
      <FormatTypes>Model</FormatTypes>
      <FormatDisclosure>
      </FormatDisclosure>
      <FormatDescription>Vectorworks is a proprietary Computer Aided Design and Building Information Modelling software program for both Mac and Windows operating systems. This software was previously called MiniCAD from 1985 - 1998 and  Vectorworks from 1999.</FormatDescription>
      <BinaryFileFormat>
      </BinaryFileFormat>
      <ByteOrders>
      </ByteOrders>
      <ReleaseDate>
      </ReleaseDate>
      <WithdrawnDate>
      </WithdrawnDate>
      <ProvenanceSourceID>224</ProvenanceSourceID>
      <ProvenanceName>Datable / Datable</ProvenanceName>
      <ProvenanceSourceDate>28 Aug 2012</ProvenanceSourceDate>
      <ProvenanceDescription>
      </ProvenanceDescription>
      <LastUpdatedDate>06 Nov 2014</LastUpdatedDate>
      <FormatNote>
      </FormatNote>
      <FormatRisk>
      </FormatRisk>
      <TechnicalEnvironment>
      </TechnicalEnvironment>
      <FileFormatIdentifier>
        <Identifier>application/vnd.vectorworks</Identifier>
        <IdentifierType>MIME</IdentifierType>
      </FileFormatIdentifier>
      <FileFormatIdentifier>
        <Identifier>fmt/1139</Identifier>
        <IdentifierType>PUID</IdentifierType>
      </FileFormatIdentifier>
      <ExternalSignature>
        <ExternalSignatureID>2162</ExternalSignatureID>
        <Signature>vwx</Signature>
        <SignatureType>File extension</SignatureType>
      </ExternalSignature>
      <InternalSignature>
        <SignatureID>1521</SignatureID>
        <SignatureName>VectorWorks 9</SignatureName>
        <SignatureNote>BOF, offset 14 'VectorWorks 9'</SignatureNote>
        <ByteSequence>
          <ByteSequenceID>1784</ByteSequenceID>
          <PositionType>Absolute from BOF</PositionType>
          <Offset>14</Offset>
          <MaxOffset>
          </MaxOffset>
          <IndirectOffsetLocation>
          </IndirectOffsetLocation>
          <IndirectOffsetLength>
          </IndirectOffsetLength>
          <Endianness>
          </Endianness>
          <ByteSequenceValue>566563746F72576F726B732039</ByteSequenceValue>
        </ByteSequence>
      </InternalSignature>
    </FileFormat>
    <SearchCriteria>Criteria</SearchCriteria>
  </report_format_detail>
</PRONOM-Report>
