<?xml version="1.0" encoding="utf-8"?>
<PRONOM-Report xmlns="http://pronom.nationalarchives.gov.uk">
  <report_format_detail>
    <FileFormat>
      <FormatID>1999</FormatID>
      <FormatName>Ogre Mesh XML</FormatName>
      <FormatVersion>
      </FormatVersion>
      <FormatAliases>
      </FormatAliases>
      <FormatFamilies>
      </FormatFamilies>
      <FormatTypes>Model</FormatTypes>
      <FormatDisclosure>
      </FormatDisclosure>
      <FormatDescription>Ogre Mesh XML is an XML-based format for representing 3D models for use within the Ogre 3D rendering engine.</FormatDescription>
      <BinaryFileFormat>
      </BinaryFileFormat>
      <ByteOrders>
      </ByteOrders>
      <ReleaseDate>
      </ReleaseDate>
      <WithdrawnDate>
      </WithdrawnDate>
      <ProvenanceSourceID>1</ProvenanceSourceID>
      <ProvenanceName>Digital Preservation Department / The National Archives</ProvenanceName>
      <ProvenanceSourceDate>10 Aug 2018</ProvenanceSourceDate>
      <ProvenanceDescription>
      </ProvenanceDescription>
      <LastUpdatedDate>10 Aug 2018</LastUpdatedDate>
      <FormatNote>
      </FormatNote>
      <FormatRisk>
      </FormatRisk>
      <TechnicalEnvironment>
      </TechnicalEnvironment>
      <FileFormatIdentifier>
        <Identifier>fmt/1189</Identifier>
        <IdentifierType>PUID</IdentifierType>
      </FileFormatIdentifier>
      <ExternalSignature>
        <ExternalSignatureID>2218</ExternalSignatureID>
        <Signature>xml</Signature>
        <SignatureType>File extension</SignatureType>
      </ExternalSignature>
      <InternalSignature>
        <SignatureID>1569</SignatureID>
        <SignatureName>Ogre Mesh XML</SignatureName>
        <SignatureNote>BOF: &lt;mesh&gt;{0-64}&lt;submeshes&gt;{0-8}&lt;submesh
EOF offset 0-3: &lt;/mesh&gt; - 
http://wiki.ogre3d.org/tiki-index.php?page=Ogre+meshxml+DTD</SignatureNote>
        <ByteSequence>
          <ByteSequenceID>1837</ByteSequenceID>
          <PositionType>Absolute from BOF</PositionType>
          <Offset>0</Offset>
          <MaxOffset>0</MaxOffset>
          <IndirectOffsetLocation>
          </IndirectOffsetLocation>
          <IndirectOffsetLength>
          </IndirectOffsetLength>
          <Endianness>
          </Endianness>
          <ByteSequenceValue>3C6D6573683E{0-64}3C7375626D65736865733E{0-8}3C7375626D657368</ByteSequenceValue>
        </ByteSequence>
        <ByteSequence>
          <ByteSequenceID>1840</ByteSequenceID>
          <PositionType>Absolute from EOF</PositionType>
          <Offset>0</Offset>
          <MaxOffset>3</MaxOffset>
          <IndirectOffsetLocation>
          </IndirectOffsetLocation>
          <IndirectOffsetLength>
          </IndirectOffsetLength>
          <Endianness>
          </Endianness>
          <ByteSequenceValue>3C2F6D6573683E</ByteSequenceValue>
        </ByteSequence>
      </InternalSignature>
    </FileFormat>
    <SearchCriteria>Criteria</SearchCriteria>
  </report_format_detail>
</PRONOM-Report>
