<?xml version="1.0" encoding="utf-8"?>
<PRONOM-Report xmlns="http://pronom.nationalarchives.gov.uk">
  <report_format_detail>
    <FileFormat>
      <FormatID>799</FormatID>
      <FormatName>Tagged Image File Format for Internet Fax (TIFF-FX)</FormatName>
      <FormatVersion>
      </FormatVersion>
      <FormatAliases>
      </FormatAliases>
      <FormatFamilies>
      </FormatFamilies>
      <FormatTypes>Image (Raster)</FormatTypes>
      <FormatDisclosure>
      </FormatDisclosure>
      <FormatDescription>The Tagged Image File for Fax Extended (TIFF-FX) format is an extension of the TIFF format.  New TIFF tags are defined to allow the mapping of Fax-specific attributes commonly associated with black and white fax and colour fax files.</FormatDescription>
      <BinaryFileFormat>Text</BinaryFileFormat>
      <ByteOrders>
      </ByteOrders>
      <ReleaseDate>
      </ReleaseDate>
      <WithdrawnDate>
      </WithdrawnDate>
      <ProvenanceSourceID>1</ProvenanceSourceID>
      <ProvenanceName>Digital Preservation Department / The National Archives</ProvenanceName>
      <ProvenanceSourceDate>02 Feb 2007</ProvenanceSourceDate>
      <ProvenanceDescription>
      </ProvenanceDescription>
      <LastUpdatedDate>01 May 2013</LastUpdatedDate>
      <FormatNote>
      </FormatNote>
      <FormatRisk>
      </FormatRisk>
      <TechnicalEnvironment>
      </TechnicalEnvironment>
      <FileFormatIdentifier>
        <Identifier>fmt/156</Identifier>
        <IdentifierType>PUID</IdentifierType>
      </FileFormatIdentifier>
      <FileFormatIdentifier>
        <Identifier>image/tiff</Identifier>
        <IdentifierType>MIME</IdentifierType>
      </FileFormatIdentifier>
      <ExternalSignature>
        <ExternalSignatureID>831</ExternalSignatureID>
        <Signature>tif</Signature>
        <SignatureType>File extension</SignatureType>
      </ExternalSignature>
      <ExternalSignature>
        <ExternalSignatureID>832</ExternalSignatureID>
        <Signature>tiff</Signature>
        <SignatureType>File extension</SignatureType>
      </ExternalSignature>
      <ExternalSignature>
        <ExternalSignatureID>1231</ExternalSignatureID>
        <Signature>tfx</Signature>
        <SignatureType>File extension</SignatureType>
      </ExternalSignature>
      <RelatedFormat>
        <RelationshipType>Has priority over</RelationshipType>
        <RelatedFormatID>672</RelatedFormatID>
        <RelatedFormatName>Exchangeable Image File Format (Uncompressed)</RelatedFormatName>
        <RelatedFormatVersion>2.2</RelatedFormatVersion>
      </RelatedFormat>
      <RelatedFormat>
        <RelationshipType>Has priority over</RelationshipType>
        <RelatedFormatID>673</RelatedFormatID>
        <RelatedFormatName>Exchangeable Image File Format (Uncompressed)</RelatedFormatName>
        <RelatedFormatVersion>2.1</RelatedFormatVersion>
      </RelatedFormat>
      <RelatedFormat>
        <RelationshipType>Has priority over</RelationshipType>
        <RelatedFormatID>752</RelatedFormatID>
        <RelatedFormatName>Exchangeable Image File Format (Uncompressed)</RelatedFormatName>
        <RelatedFormatVersion>2.0</RelatedFormatVersion>
      </RelatedFormat>
      <RelatedFormat>
        <RelationshipType>Has priority over</RelationshipType>
        <RelatedFormatID>1099</RelatedFormatID>
        <RelatedFormatName>Tagged Image File Format</RelatedFormatName>
        <RelatedFormatVersion>
        </RelatedFormatVersion>
      </RelatedFormat>
      <RelatedFormat>
        <RelationshipType>Is subtype of</RelationshipType>
        <RelatedFormatID>612</RelatedFormatID>
        <RelatedFormatName>Tagged Image File Format</RelatedFormatName>
        <RelatedFormatVersion>6</RelatedFormatVersion>
      </RelatedFormat>
    </FileFormat>
    <SearchCriteria>Criteria</SearchCriteria>
  </report_format_detail>
</PRONOM-Report>
