<?xml version="1.0" encoding="utf-8"?>
<PRONOM-Report xmlns="http://pronom.nationalarchives.gov.uk">
  <report_format_detail>
    <FileFormat>
      <FormatID>1917</FormatID>
      <FormatName>Python Compiled File</FormatName>
      <FormatVersion>2.3</FormatVersion>
      <FormatAliases>
      </FormatAliases>
      <FormatFamilies>
      </FormatFamilies>
      <FormatTypes>
      </FormatTypes>
      <FormatDisclosure>
      </FormatDisclosure>
      <FormatDescription>	Python automatically compiles a python script before running it, the first time the script runs it will create a .pyc in the same directory as the .py file which will then be used if the script is run again to save time by not having to re-compile the code.</FormatDescription>
      <BinaryFileFormat>
      </BinaryFileFormat>
      <ByteOrders>
      </ByteOrders>
      <ReleaseDate>
      </ReleaseDate>
      <WithdrawnDate>
      </WithdrawnDate>
      <ProvenanceSourceID>1</ProvenanceSourceID>
      <ProvenanceName>Digital Preservation Department / The National Archives</ProvenanceName>
      <ProvenanceSourceDate>24 Nov 2017</ProvenanceSourceDate>
      <ProvenanceDescription>
      </ProvenanceDescription>
      <LastUpdatedDate>24 Nov 2017</LastUpdatedDate>
      <FormatNote>
      </FormatNote>
      <FormatRisk>
      </FormatRisk>
      <TechnicalEnvironment>
      </TechnicalEnvironment>
      <FileFormatIdentifier>
        <Identifier>fmt/1109</Identifier>
        <IdentifierType>PUID</IdentifierType>
      </FileFormatIdentifier>
      <ExternalSignature>
        <ExternalSignatureID>2123</ExternalSignatureID>
        <Signature>pyc</Signature>
        <SignatureType>File extension</SignatureType>
      </ExternalSignature>
      <InternalSignature>
        <SignatureID>1492</SignatureID>
        <SignatureName>PYC 2.3</SignatureName>
        <SignatureNote>3BF20D0A - ;ò..</SignatureNote>
        <ByteSequence>
          <ByteSequenceID>1753</ByteSequenceID>
          <PositionType>Absolute from BOF</PositionType>
          <Offset>0</Offset>
          <MaxOffset>0</MaxOffset>
          <IndirectOffsetLocation>
          </IndirectOffsetLocation>
          <IndirectOffsetLength>
          </IndirectOffsetLength>
          <Endianness>
          </Endianness>
          <ByteSequenceValue>3BF20D0A</ByteSequenceValue>
        </ByteSequence>
      </InternalSignature>
    </FileFormat>
    <SearchCriteria>Criteria</SearchCriteria>
  </report_format_detail>
</PRONOM-Report>
